django_kelove_cms/__init__.py
django_kelove_cms/admin.py
django_kelove_cms/apps.py
django_kelove_cms/forms.py
django_kelove_cms/migrations/0001_initial.py
django_kelove_cms/migrations/__init__.py
django_kelove_cms/models.py
django_kelove_cms/settings.py
django_kelove_cms/static/kelove_cms/template-select.js
django_kelove_cms/template_settings.py
django_kelove_cms/templatetags/__init__.py
django_kelove_cms/templatetags/kelove_cms_breadcrumb.py
django_kelove_cms/templatetags/kelove_cms_document.py
django_kelove_cms/templatetags/kelove_cms_extras.py
django_kelove_cms/templatetags/kelove_cms_nav.py
django_kelove_cms/templatetags/kelove_cms_url.py
django_kelove_cms/urls.py
django_kelove_cms/util.py
django_kelove_cms/validators.py
django_kelove_cms/views.py
django_kelove_cms-0.4.0.dist-info/WHEEL
django_kelove_cms-0.4.0.dist-info/METADATA
django_kelove_cms-0.4.0.dist-info/RECORD
